README.md
setup.py
zlink
zlink.py
zlink/__init__.py
zlink/file.py
zlink/globalvars.py
zlink/note.py
zlink/zlink.py
zlink.egg-info/PKG-INFO
zlink.egg-info/SOURCES.txt
zlink.egg-info/dependency_links.txt
zlink.egg-info/entry_points.txt
zlink.egg-info/requires.txt
zlink.egg-info/top_level.txt