Metadata-Version: 1.0
Name: zlink
Version: 0.0.5
Summary: Command line zettelkasten browser/editor.
Home-page: https://github.com/pgillan145/zlink
Author: Patrick Gillan
Author-email: pgillan@minorimpact.com
License: GPLv3
Platform: UNKNOWN
